[
  {
    "title": "Monkey Man",
    "rating": 7.4,
    "tags": ["accion", "suspenso", "crimen"]
  },
  {
    "title": "Arcadian",
    "rating": 6.3,
    "tags": ["ciencia ficcion", "suspenso", "terror"]
  },
  {
    "title": "Vidas Perfectas",
    "rating": 7.4,
    "tags": ["drama", "suspenso"]
  },
  {
    "title": "Damaged",
    "rating": 4.7,
    "tags": ["accion", "suspenso", "Crimen"]
  },
  {
    "title": "Cash Out",
    "rating": 5.2,
    "tags": ["accion", "crimen", "suspenso"]
  },
  {
    "title": "Fallout",
    "rating": 8.4,
    "tags": ["accion y aventura", "misterio"]
  },
  {
    "title": "Seeat",
    "rating": 8.2,
    "tags": ["accion y aventura", "drama"]
  },
  {
    "title": "See",
    "rating": 8.2,
    "tags": ["accion y aventura", "drama"]
  },
  {
    "title": "Atrapados en el abismo",
    "rating": 6.3,
    "tags": ["accion", "terror", "suspenso"]
  },
  {
    "title": "Mision Hostil",
    "rating": 7.2,
    "tags": ["accion", "suspenso", "belica"]
  }
]
